cosmosdb/__init__.py
cosmosdb/create/__init__.py
cosmosdb/create/create.py
cosmosdb/delete/__init__.py
cosmosdb/delete/delete.py
cosmosdb/env/__init__.py
cosmosdb/env/keys.py
cosmosdb/list/__init__.py
cosmosdb/list/list.py
cosmosdb/patch/__init__.py
cosmosdb/patch/patch.py
cosmosdb/query/__init__.py
cosmosdb/query/query.py
cosmosdb/util/__init__.py
cosmosdb/util/util.py
cosmosdb-0.1.12.dist-info/METADATA
cosmosdb-0.1.12.dist-info/WHEEL
cosmosdb-0.1.12.dist-info/top_level.txt
cosmosdb-0.1.12.dist-info/RECORD
