Metadata-Version: 2.1
Name: cosmosdb
Version: 0.1.12
Summary: Python SDK for Azure Cosmos DB NoSQL
Author-email: Marcel Claramunt <marcel@moveread.com>
Project-URL: home, https://github.com/moveread/azure-sdks/tree/main/sdks/cosmosdb
Project-URL: repo, https://github.com/moveread/azure-sdks
Requires-Python: >=3.10
Requires-Dist: azure-cosmos
Requires-Dist: aiohttp
Requires-Dist: haskellian-asyn
Requires-Dist: pydantic
